webgeocalc/__init__.py
webgeocalc/api.py
webgeocalc/calculation.py
webgeocalc/calculation_types.py
webgeocalc/cli.py
webgeocalc/decorator.py
webgeocalc/direction.py
webgeocalc/errors.py
webgeocalc/payload.py
webgeocalc/types.py
webgeocalc/vars.py
webgeocalc/version.py
webgeocalc-1.5.0.dist-info/LICENSE.md
webgeocalc-1.5.0.dist-info/METADATA
webgeocalc-1.5.0.dist-info/WHEEL
webgeocalc-1.5.0.dist-info/entry_points.txt
webgeocalc-1.5.0.dist-info/top_level.txt
webgeocalc-1.5.0.dist-info/RECORD
