Metadata-Version: 2.1
Name: webgeocalc
Version: 1.5.0
Summary: Python package for NAIF WebGeoCalc API
Home-page: https://github.com/seignovert/python-webgeocalc
Author: Benoit Seignovert
Author-email: benoit.seignovert@univ-nantes.fr
License: MIT
Project-URL: Bug Tracker, https://github.com/seignovert/python-webgeocalc/issues
Project-URL: Code coverage, https://codecov.io/gh/seignovert/python-webgeocalc
Project-URL: Travis CI, https://travis-ci.org/seignovert/python-webgeocalc
Project-URL: Source Code, https://github.com/seignovert/python-webgeocalc
Project-URL: Documentation, https://webgeocalc.readthedocs.io/
Keywords: naif,webgeocalc,api
Classifier: Development Status :: 5 - Production/Stable
Classifier: Intended Audience :: Science/Research
Classifier: Intended Audience :: Developers
Classifier: License :: OSI Approved :: MIT License
Classifier: Natural Language :: English
Classifier: Programming Language :: Python
Classifier: Programming Language :: Python :: 3.11
Classifier: Topic :: Scientific/Engineering
Classifier: Topic :: Scientific/Engineering :: Astronomy
Requires-Python: >=3.11
License-File: LICENSE.md
Requires-Dist: requests>=2.31
